tamil_nlp_packages/__init__.py
tamil_nlp_packages/logger.py
tamil_nlp_packages/tam.acr
tamil_nlp_packages/tamil_tokenizer.py
tamil_nlp_packages-1.1.dist-info/LICENSE
tamil_nlp_packages-1.1.dist-info/METADATA
tamil_nlp_packages-1.1.dist-info/WHEEL
tamil_nlp_packages-1.1.dist-info/RECORD
