Metadata-Version: 2.1
Name: tamil_nlp_packages
Version: 1.1
Summary: It is a package for tokenize the tamil paragraph.
License: GNU GENERAL PUBLIC LICENSE
Author: Author
Requires-Python: >=3.6,<4.0
Classifier: License :: Other/Proprietary License
Classifier: Programming Language :: Python :: 3
Classifier: Programming Language :: Python :: 3.6
Classifier: Programming Language :: Python :: 3.7
Classifier: Programming Language :: Python :: 3.8
Classifier: Programming Language :: Python :: 3.9
Classifier: Programming Language :: Python :: 3.10
Classifier: Programming Language :: Python :: 3.11
